llm_aggregator/__init__.py
llm_aggregator/__main__.py
llm_aggregator/_version.py
llm_aggregator/api.py
llm_aggregator/cli.py
llm_aggregator/config.py
llm_aggregator/main.py
llm_aggregator/models.py
llm_aggregator/services/__init__.py
llm_aggregator/services/model_sources.py
llm_aggregator/services/model_store.py
llm_aggregator/services/stats_collector.py
llm_aggregator/services/tasks.py
llm_aggregator/services/brain_client/__init__.py
llm_aggregator/services/brain_client/brain_client.py
llm_aggregator/services/enrich_model/__init__.py
llm_aggregator/services/enrich_model/_const.py
llm_aggregator/services/enrich_model/_extract_json_object.py
llm_aggregator/services/enrich_model/_map_enrich_result.py
llm_aggregator/services/enrich_model/enrich_model.py
llm_aggregator/static/index.html
llm_aggregator/static/main.js
llm_aggregator-0.0.3.dist-info/METADATA
llm_aggregator-0.0.3.dist-info/WHEEL
llm_aggregator-0.0.3.dist-info/entry_points.txt
llm_aggregator-0.0.3.dist-info/licenses/LICENSE
llm_aggregator-0.0.3.dist-info/RECORD
