Metadata-Version: 2.4
Name: llm-aggregator
Version: 0.0.3
Summary: A model aggregator service for multiple LLM backends.
Project-URL: Homepage, https://github.com/Wuodan/llm-aggregator
Project-URL: Repository, https://github.com/Wuodan/llm-aggregator
Project-URL: Issues, https://github.com/Wuodan/llm-aggregator/issues
License: Apache-2.0
License-File: LICENSE
Requires-Python: >=3.10
Requires-Dist: aiohttp
Requires-Dist: apscheduler
Requires-Dist: fastapi
Requires-Dist: httpx
Requires-Dist: psutil
Requires-Dist: pydantic
Requires-Dist: pydantic-settings
Requires-Dist: pyyaml
Requires-Dist: uvicorn
